itkdb_pandas/__init__.py
itkdb_pandas-0.0.1.dist-info/METADATA
itkdb_pandas-0.0.1.dist-info/WHEEL
itkdb_pandas-0.0.1.dist-info/top_level.txt
itkdb_pandas-0.0.1.dist-info/RECORD
