Metadata-Version: 2.1
Name: itkdb-pandas
Version: 0.0.1
Summary: Pandas interface to the ITk Production database
Home-page: https://gitlab.cern.ch/kkrizka/itkdb-pandas
Author: Karol Krizka
Author-email: kkrizka@gmail.com
License: UNKNOWN
Platform: UNKNOWN
Classifier: Programming Language :: Python :: 3
Classifier: License :: OSI Approved :: GNU General Public License v3 (GPLv3)
Classifier: Operating System :: OS Independent
Requires-Dist: itkdb
Requires-Dist: pandas
